casting/platform/config/__init__.py
casting/platform/config/loader.py
casting/platform/config/settings.py
casting_config-0.1.0.dist-info/WHEEL
casting_config-0.1.0.dist-info/METADATA
casting_config-0.1.0.dist-info/RECORD
