Metadata-Version: 2.3
Name: casting-config
Version: 0.1.0
Summary: Simple app-level .env loader for Casting development
Requires-Dist: python-dotenv>=1.0.1
Requires-Dist: pydantic>=2.7
Requires-Dist: pydantic-settings>=2.5
Requires-Dist: pytest>=8.3.0 ; extra == 'dev'
Requires-Python: >=3.13
Provides-Extra: dev
